mikutoolkit/__init__.py
mikutoolkit/ae/__init__.py
mikutoolkit/ae/phi.py
mikutoolkit/ae/psi.py
mikutoolkit/crypto/__init__.py
mikutoolkit/crypto/phi.py
mikutoolkit/crypto/psi.py
mikutoolkit/datasets/__init__.py
mikutoolkit/datasets/phi.py
mikutoolkit/datasets/psi.py
mikutoolkit/fourier/__init__.py
mikutoolkit/fourier/phi.py
mikutoolkit/fourier/psi.py
mikutoolkit/heartland/__init__.py
mikutoolkit/heartland/phi/__init__.py
mikutoolkit/heartland/phi/fomalhaut.py
mikutoolkit/heartland/phi/orbitdance.py
mikutoolkit/heartland/psi/__init__.py
mikutoolkit/heartland/psi/fomalhaut.py
mikutoolkit/heartland/psi/orbitdance.py
mikutoolkit/hmm/__init__.py
mikutoolkit/hmm/phi.py
mikutoolkit/hmm/psi.py
mikutoolkit-0.0.8.dist-info/LICENSE
mikutoolkit-0.0.8.dist-info/METADATA
mikutoolkit-0.0.8.dist-info/WHEEL
mikutoolkit-0.0.8.dist-info/top_level.txt
mikutoolkit-0.0.8.dist-info/RECORD
