Metadata-Version: 2.1
Name: mikutoolkit
Version: 0.0.8
Summary: A Simple Toolkit
Home-page: https://github.com/sandyzikun/mikutoolkit.git
Classifier: Programming Language :: Python :: 3
Classifier: License :: OSI Approved :: GNU General Public License v3 (GPLv3)
License-File: LICENSE
Requires-Dist: numpy (>=1.14.3)
Requires-Dist: matplotlib (>=2.2.2)
